{"grid":[[{"type":"line","line":0,"dir":null},{"type":"line","line":0,"dir":null},{"type":"line","line":1,"dir":"right"},{"type":"line","line":1,"dir":"top"},{"type":"line","line":1,"dir":"top"},{"type":"line","line":0,"dir":null},{"type":"line","line":1,"dir":"right"},{"type":"line","line":1,"dir":"top"},{"type":"line","line":1,"dir":"top","start":true}],[{"type":"line","line":0,"dir":null},{"type":"square","color":"black","line":0,"dir":null},{"type":"line","line":1,"dir":"right"},{"type":"star","color":"black","line":0,"dir":null},{"type":"line","line":1,"dir":"left"},null,{"type":"line","line":1,"dir":"right"},null,{"type":"line","line":0,"dir":null}],[{"type":"line","line":0,"dir":null,"dot":-1},{"type":"line","line":0,"dir":null},{"type":"line","line":1,"dir":"right","dot":null,"end":null,"start":null,"gap":null},{"type":"line","line":0,"dir":null},{"type":"line","line":1,"dir":"left"},{"type":"line","line":0,"dir":null},{"type":"line","line":1,"dir":"down"},{"type":"line","line":1,"dir":"down"},{"type":"line","line":1,"dir":"right"}],[{"type":"line","line":0,"dir":null},null,{"type":"line","line":1,"dir":"right"},{"type":"twobytwo","color":"#cccccc","line":0,"dir":null},{"type":"line","line":1,"dir":"left","gap":null,"dot":null,"start":null,"end":null},{"type":"twobytwo","color":"#cccccc","line":0,"dir":null},{"type":"line","line":0,"dir":null},{"type":"star","color":"white","line":0,"dir":null},{"type":"line","line":1,"dir":"right"}],[{"type":"line","line":1,"dir":"right"},{"type":"line","line":1,"dir":"top"},{"type":"line","line":1,"dir":"top"},{"type":"line","line":0,"dir":null,"gap":null,"dot":null,"start":null,"end":null},{"type":"line","line":1,"dir":"left","start":false,"end":null},{"type":"line","line":0,"dir":null,"gap":null,"dot":null,"start":null,"end":null},{"type":"line","line":1,"dir":"right"},{"type":"line","line":1,"dir":"top"},{"type":"line","line":1,"dir":"top"}],[{"type":"line","line":1,"dir":"right"},{"type":"star","color":"black","line":0,"dir":null},{"type":"line","line":0,"dir":null},{"type":"twobytwo","color":"#cccccc","line":0,"dir":null},{"type":"line","line":1,"dir":"left","gap":null,"dot":null,"start":null,"end":null},{"type":"twobytwo","color":"#cccccc","line":0,"dir":null},{"type":"line","line":1,"dir":"right"},null,{"type":"line","line":0,"dir":null}],[{"type":"line","line":1,"dir":"down"},{"type":"line","line":1,"dir":"down"},{"type":"line","line":1,"dir":"right"},{"type":"line","line":0,"dir":null},{"type":"line","line":1,"dir":"left"},{"type":"line","line":0,"dir":null,"end":null,"start":null,"dot":null,"gap":null},{"type":"line","line":1,"dir":"right","dot":null,"end":null,"start":null,"gap":null},{"type":"line","line":0,"dir":null},{"type":"line","line":0,"dir":null,"dot":-1}],[{"type":"line","line":0,"dir":null},null,{"type":"line","line":1,"dir":"right"},{"type":"square","color":"white","line":0,"dir":null},{"type":"line","line":1,"dir":"left"},{"type":"star","color":"white","line":0,"dir":null},{"type":"line","line":1,"dir":"right"},null,{"type":"line","line":0,"dir":null}],[{"type":"line","line":1,"dir":null,"end":"top"},{"type":"line","line":1,"dir":"top"},{"type":"line","line":1,"dir":"top"},{"type":"line","line":0,"dir":null},{"type":"line","line":1,"dir":"left"},{"type":"line","line":1,"dir":"top"},{"type":"line","line":1,"dir":"top"},{"type":"line","line":0,"dir":null},{"type":"line","line":0,"dir":null}]],"largezero":162,"width":9,"height":9,"pillar":false,"settings":{"NEGATIONS_CANCEL_NEGATIONS":true,"SHAPELESS_ZERO_POLY":false,"PRECISE_POLYOMINOS":true,"FLASH_FOR_ERRORS":true,"FAT_STARTPOINTS":false},"name":"e","theme":"introduction","hasNegations":false,"hasPolyominos":false,"startPoint":{"x":0,"y":8},"endPoint":{"x":8,"y":0},"valid":false,"hasSizers":false,"invalidElements":[{"x":2,"y":0}],"negations":[],"autoSolved":true,"path":[{"x":0,"y":8},3,3,2,2,4,4,2,2,3,3,2,2,2,2,3,3,1,1,1,1,1,1,1,1,3,3,2,2,2,2,3,3,2,2,4,4,2,2,3,3,0]}